README.md
setup.cfg
setup.py
googleparser/__init__.py
googleparser/googleparser.py
googleparser.egg-info/PKG-INFO
googleparser.egg-info/SOURCES.txt
googleparser.egg-info/dependency_links.txt
googleparser.egg-info/requires.txt
googleparser.egg-info/top_level.txt