Metadata-Version: 2.1
Name: googleparser
Version: 0.2
Summary: Module for parsing google search results without access to Google Search API
Home-page: https://github.com/sidan93/googleparser
Author: Sidorov A.B.
Author-email: sidan93@gmail.com
License: MIT
Download-URL: https://github.com/sidan93/googleparser/archive/v0.1.tar.gz
Keywords: google,parser,search,google search,google parser,googleparser,googlesearch
Platform: UNKNOWN
Classifier: Development Status :: 4 - Beta
Classifier: Intended Audience :: Developers
Classifier: Topic :: Software Development :: Build Tools
Classifier: License :: OSI Approved :: MIT License
Classifier: Programming Language :: Python :: 3
Classifier: Programming Language :: Python :: 3.4
Classifier: Programming Language :: Python :: 3.5
Classifier: Programming Language :: Python :: 3.6
Classifier: Programming Language :: Python :: 3.7
